odoo/addons/purchase_invoicing_no_zero_line/__init__.py
odoo/addons/purchase_invoicing_no_zero_line/__manifest__.py
odoo/addons/purchase_invoicing_no_zero_line/i18n/de.po
odoo/addons/purchase_invoicing_no_zero_line/i18n/es.po
odoo/addons/purchase_invoicing_no_zero_line/i18n/purchase_invoicing_no_zero_line.pot
odoo/addons/purchase_invoicing_no_zero_line/models/__init__.py
odoo/addons/purchase_invoicing_no_zero_line/models/account_invoice.py
odoo/addons/purchase_invoicing_no_zero_line/models/account_journal.py
odoo/addons/purchase_invoicing_no_zero_line/static/description/icon.png
odoo/addons/purchase_invoicing_no_zero_line/static/description/icon.svg
odoo/addons/purchase_invoicing_no_zero_line/views/account_view.xml
odoo11_addon_purchase_invoicing_no_zero_line-11.0.1.0.0.99.dev7.dist-info/METADATA
odoo11_addon_purchase_invoicing_no_zero_line-11.0.1.0.0.99.dev7.dist-info/RECORD
odoo11_addon_purchase_invoicing_no_zero_line-11.0.1.0.0.99.dev7.dist-info/WHEEL
odoo11_addon_purchase_invoicing_no_zero_line-11.0.1.0.0.99.dev7.dist-info/top_level.txt
