Metadata-Version: 2.1
Name: odoo11-addon-purchase-invoicing-no-zero-line
Version: 11.0.1.0.0.99.dev7
Summary: Avoid creation of zero quantity invoice lines from purchase
Home-page: UNKNOWN
Author: Digital5 S.L., Odoo Community Association (OCA)
Author-email: support@odoo-community.org
License: AGPL-3
Platform: UNKNOWN
Classifier: Programming Language :: Python
Classifier: Framework :: Odoo
Classifier: License :: OSI Approved :: GNU Affero General Public License v3
Requires-Python: >=2.7, !=3.0.*, !=3.1.*, !=3.2.*, !=3.3.*, !=3.4.*
Requires-Dist: odoo (<11.1dev,>=11.0a)
